nova_python_sdk/__init__.py
nova_python_sdk/foo.py
nova_sdk-0.0.1.dist-info/LICENSE
nova_sdk-0.0.1.dist-info/METADATA
nova_sdk-0.0.1.dist-info/WHEEL
nova_sdk-0.0.1.dist-info/RECORD
