Metadata-Version: 2.1
Name: nova-sdk
Version: 0.0.1
Summary: This is a template repository for Python projects that use Poetry for their dependency management.
Home-page: https://github.com/Solidi-Labs/nova-python-sdk
Author: Solidi Labs
Author-email: lakonema2000@gmail.com
Requires-Python: >=3.8,<4.0
Classifier: Programming Language :: Python :: 3
Classifier: Programming Language :: Python :: 3.8
Classifier: Programming Language :: Python :: 3.9
Classifier: Programming Language :: Python :: 3.10
Classifier: Programming Language :: Python :: 3.11
Classifier: Programming Language :: Python :: 3.12
Project-URL: Documentation, https://lakonema2000.github.io/nova-python-sdk/
Project-URL: Repository, https://github.com/Solidi-Labs/nova-python-sdk
